.installed.cfg
.mr.developer.cfg
.travis.yml
MANIFEST.in
README.rst
bootstrap.py
buildout.cfg
pre-commit-check.sh
setup.cfg
setup.py
buildout.d/base.cfg
buildout.d/development.cfg
buildout.d/travis.cfg
buildout.d/versions.cfg
docs/HISTORY.rst
docs/LICENSE.rst
docs/add_plone_site.rst
docs/chapter_0.rst
docs/chapter_1.rst
docs/chapter_2.rst
docs/chapter_3.rst
docs/chapter_4.rst
docs/conf.py
docs/contribute.rst
docs/conventions.rst
docs/index.rst
docs/release.rst
docs/tutorial.rst
docs/_static/lineblock.css
docs/images/add_completed.jpg
docs/images/add_content_type.jpg
docs/images/add_folder_menu.jpg
docs/images/add_new_field.jpg
docs/images/add_open.jpg
docs/images/add_plone_site.jpg
docs/images/add_todo_content_type.jpg
docs/images/add_todo_field.jpg
docs/images/add_todo_item.jpg
docs/images/add_todo_workflow.jpg
docs/images/add_transitions.jpg
docs/images/ajax_call.jpg
docs/images/back_to_workflow.jpg
docs/images/behaviors_config.jpg
docs/images/check_workflow.jpg
docs/images/cleanup_states.jpg
docs/images/complete_details.jpg
docs/images/copy_workflow.jpg
docs/images/create_plone_site.jpg
docs/images/custom_view.jpg
docs/images/deactivate.jpg
docs/images/default_workflow.jpg
docs/images/dexterity_export.jpg
docs/images/dexterity_extension.jpg
docs/images/edit_complete.jpg
docs/images/edit_completed.jpg
docs/images/edit_reopen.jpg
docs/images/edit_todo_item.jpg
docs/images/edit_todo_workflow.jpg
docs/images/enter_portal_setup.jpg
docs/images/export_todo.jpg
docs/images/export_workflow_example.jpg
docs/images/final_todo_fields_config.jpg
docs/images/find_addons.jpg
docs/images/home_base.jpg
docs/images/initial_state.jpg
docs/images/install_todo.jpg
docs/images/live_search_title.jpg
docs/images/manage_portal_workflow.jpg
docs/images/map_to_workflow.jpg
docs/images/modify_todo_fields.jpg
docs/images/plone_configuration_panel.jpg
docs/images/portal_workflow_contents.jpg
docs/images/reactivate.jpg
docs/images/rename_workflow.jpg
docs/images/retitle_workflow.jpg
src/tutorial.todoapp.egg-info/PKG-INFO
src/tutorial.todoapp.egg-info/SOURCES.txt
src/tutorial.todoapp.egg-info/dependency_links.txt
src/tutorial.todoapp.egg-info/entry_points.txt
src/tutorial.todoapp.egg-info/namespace_packages.txt
src/tutorial.todoapp.egg-info/not-zip-safe
src/tutorial.todoapp.egg-info/requires.txt
src/tutorial.todoapp.egg-info/top_level.txt
