Metadata-Version: 1.0
Name: tutorial.todoapp
Version: 1.0
Summary: A simple ToDo app tutorial for Plone.
Home-page: http://githib.com/collective/tutorial.todoapp
Author: Caipirinha Sprinters
Author-email: plone-users@lists.sourceforge.net
License: BSD
Keywords: Plone Python
Platform: UNKNOWN
Classifier: Framework :: Plone
Classifier: Programming Language :: Python
